1_pc_practice/rom.v
module rom(
    input ce,
    input [5:0] addr,

    output reg [31:0] inst
);

reg [31:0] rom [63:0];

initial $readmemh("rom.data", rom);

always @(*)
    inst <= (ce) ? rom[addr] : 32'h0;

endmodule

1_pc_practice/pc.v
module pc_reg(
    input clk,
    input rst,
    
    output reg [5:0] pc,
    output reg ce
);

always @(posedge clk or posedge rst) begin
    ce <= (rst) ? 1'b0 : 1'b1;
    pc <= (ce) ? pc + 1'b1 : 6'h0;
end

endmodule

1_pc_practice/inst_fetch.v
module inst_fetch(
    input clk,
    input rst,
    
    output [31:0] inst_o
);

wire [5:0] pc;
wire rom_ce;

pc_reg pc0(
    .clk(clk),
    .rst(rst),
    
    .pc(pc),
    .ce(rom_ce)
);

rom rom0(
    .ce(rom_ce),
    .addr(pc),

    .inst(inst_o)
);

endmodule

1_pc_practice/inst_fetch_tb.v
module inst_fetch_tb;
reg CLOCK;
reg rst;
wire [31:0] inst;

initial begin
    CLOCK = 1'b0;
    forever #10 CLOCK = ~CLOCK;
end

initial begin
    rst = 1'b1;
    #195 rst = 1'b0;
    #1000 $stop;
end

inst_fetch inst_fetch0(
    .clk(CLOCK),
    .rst(rst),
    
    .inst_o(inst)
);

initial begin
    $monitor($time, "inst = %h",inst);
end

initial begin
    $dumpfile("inst_fetch.vcd");
    $dumpvars;
end
endmodule

1_pc_practice/inst_fetch.vcd
$date
	Wed Sep  4 03:01:39 2024
$end
$version
	Icarus Verilog
$end
$timescale
	1s
$end
$scope module inst_fetch_tb $end
$var wire 32 ! inst [31:0] $end
$var reg 1 " CLOCK $end
$var reg 1 # rst $end
$scope module inst_fetch0 $end
$var wire 1 " clk $end
$var wire 1 # rst $end
$var wire 1 $ rom_ce $end
$var wire 6 % pc [5:0] $end
$var wire 32 & inst_o [31:0] $end
$scope module pc0 $end
$var wire 1 " clk $end
$var wire 1 # rst $end
$var reg 1 $ ce $end
$var reg 6 ' pc [5:0] $end
$upscope $end
$scope module rom0 $end
$var wire 6 ( addr [5:0] $end
$var wire 1 $ ce $end
$var reg 32 ) inst [31:0] $end
$upscope $end
$upscope $end
$upscope $end
$enddefinitions $end
#0
$dumpvars
b0 )
bx (
bx '
b0 &
bx %
0$
1#
0"
b0 !
$end
#10
b0 %
b0 '
b0 (
1"
#20
0"
#30
1"
#40
0"
#50
1"
#60
0"
#70
1"
#80
0"
#90
1"
#100
0"
#110
1"
#120
0"
#130
1"
#140
0"
#150
1"
#160
0"
#170
1"
#180
0"
#190
1"
#195
0#
#200
0"
#210
1$
1"
#220
0"
#230
b1000000010000000100000001 !
b1000000010000000100000001 &
b1000000010000000100000001 )
b1 %
b1 '
b1 (
1"
#240
0"
#250
b10000000100000001000000010 !
b10000000100000001000000010 &
b10000000100000001000000010 )
b10 %
b10 '
b10 (
1"
#260
0"
#270
b11000000110000001100000011 !
b11000000110000001100000011 &
b11000000110000001100000011 )
b11 %
b11 '
b11 (
1"
#280
0"
#290
b100000001000000010000000100 !
b100000001000000010000000100 &
b100000001000000010000000100 )
b100 %
b100 '
b100 (
1"
#300
0"
#310
b101000001010000010100000101 !
b101000001010000010100000101 &
b101000001010000010100000101 )
b101 %
b101 '
b101 (
1"
#320
0"
#330
b110000001100000011000000110 !
b110000001100000011000000110 &
b110000001100000011000000110 )
b110 %
b110 '
b110 (
1"
#340
0"
#350
b111000001110000011100000111 !
b111000001110000011100000111 &
b111000001110000011100000111 )
b111 %
b111 '
b111 (
1"
#360
0"
#370
b1000000010000000100000001000 !
b1000000010000000100000001000 &
b1000000010000000100000001000 )
b1000 %
b1000 '
b1000 (
1"
#380
0"
#390
b1001000010010000100100001001 !
b1001000010010000100100001001 &
b1001000010010000100100001001 )
b1001 %
b1001 '
b1001 (
1"
#400
0"
#410
b1010000010100000101000001010 !
b1010000010100000101000001010 &
b1010000010100000101000001010 )
b1010 %
b1010 '
b1010 (
1"
#420
0"
#430
b1011000010110000101100001011 !
b1011000010110000101100001011 &
b1011000010110000101100001011 )
b1011 %
b1011 '
b1011 (
1"
#440
0"
#450
b1100000011000000110000001100 !
b1100000011000000110000001100 &
b1100000011000000110000001100 )
b1100 %
b1100 '
b1100 (
1"
#460
0"
#470
b1101000011010000110100001101 !
b1101000011010000110100001101 &
b1101000011010000110100001101 )
b1101 %
b1101 '
b1101 (
1"
#480
0"
#490
b1110000011100000111000001110 !
b1110000011100000111000001110 &
b1110000011100000111000001110 )
b1110 %
b1110 '
b1110 (
1"
#500
0"
#510
b1111000011110000111100001111 !
b1111000011110000111100001111 &
b1111000011110000111100001111 )
b1111 %
b1111 '
b1111 (
1"
#520
0"
#530
b10000000100000001000000010000 !
b10000000100000001000000010000 &
b10000000100000001000000010000 )
b10000 %
b10000 '
b10000 (
1"
#5#1195
#550
b10001000100010001000100010001 !
b10001000100010001000100010001 &
b10001000100010001000100010001 )
b10001 %
b10001 '
b10001 (
1"
#560
0"
#570
b10010000100100001001000010010 !
b10010000100100001001000010010 &
b10010000100100001001000010010 )
b10010 %
b10010 '
b10010 (
1"
#580
0"
#590
b10011000100110001001100010011 !
b10011000100110001001100010011 &
b10011000100110001001100010011 )
b10011 %
b10011 '
b10011 (
1"
#600
0"
#610
b10100000101000001010000010100 !
b10100000101000001010000010100 &
b10100000101000001010000010100 )
b10100 %
b10100 '
b10100 (
1"
#620
0"
#630
b10101000101010001010100010101 !
b10101000101010001010100010101 &
b10101000101010001010100010101 )
b10101 %
b10101 '
b10101 (
1"
#640
0"
#650
b10110000101100001011000010110 !
b10110000101100001011000010110 &
b10110000101100001011000010110 )
b10110 %
b10110 '
b10110 (
1"
#660
0"
#670
b10111000101110001011100010111 !
b10111000101110001011100010111 &
b10111000101110001011100010111 )
b10111 %
b10111 '
b10111 (
1"
#680
0"
#690
b11000000110000001100000011000 !
b11000000110000001100000011000 &
b11000000110000001100000011000 )
b11000 %
b11000 '
b11000 (
1"
#700
0"
#710
b11001000110010001100100011001 !
b11001000110010001100100011001 &
b11001000110010001100100011001 )
b11001 %
b11001 '
b11001 (
1"
#720
0"
#730
b11010000110100001101000011010 !
b11010000110100001101000011010 &
b11010000110100001101000011010 )
b11010 %
b11010 '
b11010 (
1"
#740
0"
#750
b11011000110110001101100011011 !
b11011000110110001101100011011 &
b11011000110110001101100011011 )
b11011 %
b11011 '
b11011 (
1"
#760
0"
#770
b11100000111000001110000011100 !
b11100000111000001110000011100 &
b11100000111000001110000011100 )
b11100 %
b11100 '
b11100 (
1"
#780
0"
#790
b11101000111010001110100011101 !
b11101000111010001110100011101 &
b11101000111010001110100011101 )
b11101 %
b11101 '
b11101 (
1"
#800
0"
#810
b11110000111100001111000011110 !
b11110000111100001111000011110 &
b11110000111100001111000011110 )
b11110 %
b11110 '
b11110 (
1"
#820
0"
#830
b11111000111110001111100011111 !
b11111000111110001111100011111 &
b11111000111110001111100011111 )
b11111 %
b11111 '
b11111 (
1"
#840
0"
#850
b100000001000000010000000100000 !
b100000001000000010000000100000 &
b100000001000000010000000100000 )
b100000 %
b100000 '
b100000 (
1"
#860
0"
#870
b100001001000010010000100100001 !
b100001001000010010000100100001 &
b100001001000010010000100100001 )
b100001 %
b100001 '
b100001 (
1"
#880
0"
#890
b100010001000100010001000100010 !
b100010001000100010001000100010 &
b100010001000100010001000100010 )
b100010 %
b100010 '
b100010 (
1"
#900
0"
#910
b100011001000110010001100100011 !
b100011001000110010001100100011 &
b100011001000110010001100100011 )
b100011 %
b100011 '
b100011 (
1"
#920
0"
#930
b100100001001000010010000100100 !
b100100001001000010010000100100 &
b100100001001000010010000100100 )
b100100 %
b100100 '
b100100 (
1"
#940
0"
#950
b100101001001010010010100100101 !
b100101001001010010010100100101 &
b100101001001010010010100100101 )
b100101 %
b100101 '
b100101 (
1"
#960
0"
#970
b100110001001100010011000100110 !
b100110001001100010011000100110 &
b100110001001100010011000100110 )
b100110 %
b100110 '
b100110 (
1"
#980
0"
#990
b100111001001110010011100100111 !
b100111001001110010011100100111 &
b100111001001110010011100100111 )
b100111 %
b100111 '
b100111 (
1"
#1000
0"
#1010
b101000001010000010100000101000 !
b101000001010000010100000101000 &
b101000001010000010100000101000 )
b101000 %
b101000 '
b101000 (
1"
#1020
0"
#1030
b101001001010010010100100101001 !
b101001001010010010100100101001 &
b101001001010010010100100101001 )
b101001 %
b101001 '
b101001 (
1"
#1040
0"
#1050
b101010001010100010101000101010 !
b101010001010100010101000101010 &
b101010001010100010101000101010 )
b101010 %
b101010 '
b101010 (
1"
#1060
0"
#1070
b101011001010110010101100101011 !
b101011001010110010101100101011 &
b101011001010110010101100101011 )
b101011 %
b101011 '
b101011 (
1"
#1080
0"
#1090
b101100001011000010110000101100 !
b101100001011000010110000101100 &
b101100001011000010110000101100 )
b101100 %
b101100 '
b101100 (
1"
#1100
0"
#1110
b101101001011010010110100101101 !
b101101001011010010110100101101 &
b101101001011010010110100101101 )
b101101 %
b101101 '
b101101 (
1"
#1120
0"
#1130
b101110001011100010111000101110 !
b101110001011100010111000101110 &
b101110001011100010111000101110 )
b101110 %
b101110 '
b101110 (
1"
#1140
0"
#1150
b101111001011110010111100101111 !
b101111001011110010111100101111 &
b101111001011110010111100101111 )
b101111 %
b101111 '
b101111 (
1"
#1160
0"
#1170
b110000001100000011000000110000 !
b110000001100000011000000110000 &
b110000001100000011000000110000 )
b110000 %
b110000 '
b110000 (
1"
#1180
0"
#1190
b110001001100010011000100110001 !
b110001001100010011000100110001 &
b110001001100010011000100110001 )
b110001 %
b110001 '
b110001 (
1"
